patina/__init__.py
patina/_utils.py
patina/hashmap.py
patina/option.py
patina/py.typed
patina/ref.py
patina/result.py
patina-0.5.0.dist-info/LICENSE
patina-0.5.0.dist-info/WHEEL
patina-0.5.0.dist-info/METADATA
patina-0.5.0.dist-info/RECORD
