Metadata-Version: 2.1
Name: patina
Version: 0.5.0
Summary: Rusty types for Python
Home-page: https://github.com/p7g/patina
License: MIT
Author: Patrick Gingras
Author-email: 775.pg.12@gmail.com
Requires-Python: >=3.6,<4.0
Classifier: Intended Audience :: Developers
Classifier: License :: OSI Approved :: MIT License
Classifier: Programming Language :: Python :: 3
Classifier: Programming Language :: Python :: 3.6
Classifier: Programming Language :: Python :: 3.7
Classifier: Programming Language :: Python :: 3.8
Classifier: Programming Language :: Python :: 3.9
Classifier: Topic :: Software Development :: Libraries :: Python Modules
Classifier: Typing :: Typed
Project-URL: Documentation, https://patina.rtfd.io
Project-URL: Repository, https://github.com/p7g/patina
